pycalcul/pycalcul.py
pycalcul-3.0.dist-info/METADATA
pycalcul-3.0.dist-info/WHEEL
pycalcul-3.0.dist-info/RECORD
